;.source
.class public static myResult
.super java/lang/Object
.method public static main([Ljava/lang/String;)V
.limit stack 22
.limit locals 22
ldc 12.0
f2d
dstore 0
ldc 2.3
f2d
dstore 2
ldc 2.6
f2d
dstore 4
ldc 1.0
fstore 6
ldc 2.0
fstore 7
ldc 1
istore 8
ldc 2
istore 9
ldc 5.0
f2d
dstore 0
getstatic java/lang/System/out Ljava/io/PrintStream;
ldc ""
invokevirtual java/io/PrintStream/print(Ljava/lang/String;)V
getstatic java/lang/System/out Ljava/io/PrintStream;
dload 0
invokevirtual java/io/PrintStream/print(D)V
getstatic java/lang/System/out Ljava/io/PrintStream;
ldc "\n"
invokevirtual java/io/PrintStream/print(Ljava/lang/String;)V
ldc 1.25
f2d
dload 0
dadd
dstore 0
dload 0
ldc 1.25
f2d
dadd
dstore 0
getstatic java/lang/System/out Ljava/io/PrintStream;
ldc ""
invokevirtual java/io/PrintStream/print(Ljava/lang/String;)V
getstatic java/lang/System/out Ljava/io/PrintStream;
dload 0
invokevirtual java/io/PrintStream/print(D)V
getstatic java/lang/System/out Ljava/io/PrintStream;
ldc "\n"
invokevirtual java/io/PrintStream/print(Ljava/lang/String;)V
ldc 1.75
f2d
dload 0
dsub
dneg
dstore 0
dload 0
ldc 1.75
f2d
dsub
dstore 0
getstatic java/lang/System/out Ljava/io/PrintStream;
ldc ""
invokevirtual java/io/PrintStream/print(Ljava/lang/String;)V
getstatic java/lang/System/out Ljava/io/PrintStream;
dload 0
invokevirtual java/io/PrintStream/print(D)V
getstatic java/lang/System/out Ljava/io/PrintStream;
ldc "\n"
invokevirtual java/io/PrintStream/print(Ljava/lang/String;)V
ldc 2.1
f2d
dload 0
dmul
dstore 0
dload 0
ldc 1.0
f2d
dmul
dstore 0
getstatic java/lang/System/out Ljava/io/PrintStream;
ldc ""
invokevirtual java/io/PrintStream/print(Ljava/lang/String;)V
getstatic java/lang/System/out Ljava/io/PrintStream;
dload 0
invokevirtual java/io/PrintStream/print(D)V
getstatic java/lang/System/out Ljava/io/PrintStream;
ldc "\n"
invokevirtual java/io/PrintStream/print(Ljava/lang/String;)V
dload 0
ldc 4.2
f2d
ddiv
dstore 0
getstatic java/lang/System/out Ljava/io/PrintStream;
ldc ""
invokevirtual java/io/PrintStream/print(Ljava/lang/String;)V
getstatic java/lang/System/out Ljava/io/PrintStream;
dload 0
invokevirtual java/io/PrintStream/print(D)V
getstatic java/lang/System/out Ljava/io/PrintStream;
ldc "\n"
invokevirtual java/io/PrintStream/print(Ljava/lang/String;)V
dload 0
ldc 1.5
f2d
drem
dstore 0
getstatic java/lang/System/out Ljava/io/PrintStream;
ldc ""
invokevirtual java/io/PrintStream/print(Ljava/lang/String;)V
getstatic java/lang/System/out Ljava/io/PrintStream;
dload 0
invokevirtual java/io/PrintStream/print(D)V
getstatic java/lang/System/out Ljava/io/PrintStream;
ldc "\n"
invokevirtual java/io/PrintStream/print(Ljava/lang/String;)V
dload 0
ldc 1.0
f2d
dadd
dstore 0
getstatic java/lang/System/out Ljava/io/PrintStream;
ldc ""
invokevirtual java/io/PrintStream/print(Ljava/lang/String;)V
getstatic java/lang/System/out Ljava/io/PrintStream;
dload 0
invokevirtual java/io/PrintStream/print(D)V
getstatic java/lang/System/out Ljava/io/PrintStream;
ldc "\n"
invokevirtual java/io/PrintStream/print(Ljava/lang/String;)V
dload 0
ldc 1.0
f2d
dsub
dstore 0
getstatic java/lang/System/out Ljava/io/PrintStream;
ldc ""
invokevirtual java/io/PrintStream/print(Ljava/lang/String;)V
getstatic java/lang/System/out Ljava/io/PrintStream;
dload 0
invokevirtual java/io/PrintStream/print(D)V
getstatic java/lang/System/out Ljava/io/PrintStream;
ldc "\n"
invokevirtual java/io/PrintStream/print(Ljava/lang/String;)V
dload 0
ldc 1.0
f2d
dadd
dstore 0
getstatic java/lang/System/out Ljava/io/PrintStream;
ldc ""
invokevirtual java/io/PrintStream/print(Ljava/lang/String;)V
getstatic java/lang/System/out Ljava/io/PrintStream;
dload 0
invokevirtual java/io/PrintStream/print(D)V
getstatic java/lang/System/out Ljava/io/PrintStream;
ldc "\n"
invokevirtual java/io/PrintStream/print(Ljava/lang/String;)V
dload 0
ldc 1.0
f2d
dsub
dstore 0
getstatic java/lang/System/out Ljava/io/PrintStream;
ldc ""
invokevirtual java/io/PrintStream/print(Ljava/lang/String;)V
getstatic java/lang/System/out Ljava/io/PrintStream;
dload 0
invokevirtual java/io/PrintStream/print(D)V
getstatic java/lang/System/out Ljava/io/PrintStream;
ldc "\n"
invokevirtual java/io/PrintStream/print(Ljava/lang/String;)V
dload 0
dneg
dstore 0
getstatic java/lang/System/out Ljava/io/PrintStream;
ldc ""
invokevirtual java/io/PrintStream/print(Ljava/lang/String;)V
getstatic java/lang/System/out Ljava/io/PrintStream;
dload 0
invokevirtual java/io/PrintStream/print(D)V
getstatic java/lang/System/out Ljava/io/PrintStream;
ldc "\n"
invokevirtual java/io/PrintStream/print(Ljava/lang/String;)V
ldc 0.0
f2d
dstore 0
ldc 0
istore 11
Loop0:
iload 11
ldc 10
if_icmpge ELSE0
ldc 1.0
f2d
dload 0
dadd
dstore 0
iload 11
ldc 1
iadd
istore 11
goto Loop0
ELSE0:
getstatic java/lang/System/out Ljava/io/PrintStream;
ldc "FOR: i = "
invokevirtual java/io/PrintStream/print(Ljava/lang/String;)V
getstatic java/lang/System/out Ljava/io/PrintStream;
iload 11
invokevirtual java/io/PrintStream/print(I)V
getstatic java/lang/System/out Ljava/io/PrintStream;
ldc ", a = "
invokevirtual java/io/PrintStream/print(Ljava/lang/String;)V
getstatic java/lang/System/out Ljava/io/PrintStream;
dload 0
invokevirtual java/io/PrintStream/print(D)V
getstatic java/lang/System/out Ljava/io/PrintStream;
ldc "\n"
invokevirtual java/io/PrintStream/print(Ljava/lang/String;)V
ldc 0.0
f2d
dstore 0
Loop1:
iload 11
ldc 0
if_icmple ELSE1
ldc 2.0
f2d
dload 0
dadd
dstore 0
iload 11
ldc 1
isub
istore 11
goto Loop1
ELSE1:
getstatic java/lang/System/out Ljava/io/PrintStream;
ldc "WHILE: i = "
invokevirtual java/io/PrintStream/print(Ljava/lang/String;)V
getstatic java/lang/System/out Ljava/io/PrintStream;
iload 11
invokevirtual java/io/PrintStream/print(I)V
getstatic java/lang/System/out Ljava/io/PrintStream;
ldc ", a = "
invokevirtual java/io/PrintStream/print(Ljava/lang/String;)V
getstatic java/lang/System/out Ljava/io/PrintStream;
dload 0
invokevirtual java/io/PrintStream/print(D)V
getstatic java/lang/System/out Ljava/io/PrintStream;
ldc "\n"
invokevirtual java/io/PrintStream/print(Ljava/lang/String;)V
dload 0
ldc 0.0
f2d
dcmpl
ifle ELSE2
getstatic java/lang/System/out Ljava/io/PrintStream;
ldc "in_1\n"
invokevirtual java/io/PrintStream/print(Ljava/lang/String;)V
dload 0
ldc 5.0
f2d
dcmpl
iflt ELSE3
getstatic java/lang/System/out Ljava/io/PrintStream;
ldc "in_2\n"
invokevirtual java/io/PrintStream/print(Ljava/lang/String;)V
dload 0
ldc 10.0
f2d
dcmpl
ifge ELSE4
getstatic java/lang/System/out Ljava/io/PrintStream;
ldc "in_3\n"
invokevirtual java/io/PrintStream/print(Ljava/lang/String;)V
goto END2
ELSE4:
getstatic java/lang/System/out Ljava/io/PrintStream;
ldc "out_3\n"
invokevirtual java/io/PrintStream/print(Ljava/lang/String;)V
END2:
goto END1
ELSE3:
getstatic java/lang/System/out Ljava/io/PrintStream;
ldc "out_2\n"
invokevirtual java/io/PrintStream/print(Ljava/lang/String;)V
END1:
getstatic java/lang/System/out Ljava/io/PrintStream;
ldc "out_1\n"
invokevirtual java/io/PrintStream/print(Ljava/lang/String;)V
goto END0
ELSE2:
getstatic java/lang/System/out Ljava/io/PrintStream;
ldc "out_0\n"
invokevirtual java/io/PrintStream/print(Ljava/lang/String;)V
END0:
ldc 3.0
fstore 10
dload 2
ldc 1.0
f2d
dadd
dload 4
dmul
dstore 0
getstatic java/lang/System/out Ljava/io/PrintStream;
ldc "a = "
invokevirtual java/io/PrintStream/print(Ljava/lang/String;)V
getstatic java/lang/System/out Ljava/io/PrintStream;
dload 0
invokevirtual java/io/PrintStream/print(D)V
getstatic java/lang/System/out Ljava/io/PrintStream;
ldc "\n"
invokevirtual java/io/PrintStream/print(Ljava/lang/String;)V
dload 2
ldc 1.5
f2d
dload 4
dmul
dadd
dstore 0
getstatic java/lang/System/out Ljava/io/PrintStream;
ldc "a = "
invokevirtual java/io/PrintStream/print(Ljava/lang/String;)V
getstatic java/lang/System/out Ljava/io/PrintStream;
dload 0
invokevirtual java/io/PrintStream/print(D)V
getstatic java/lang/System/out Ljava/io/PrintStream;
ldc "\n"
invokevirtual java/io/PrintStream/print(Ljava/lang/String;)V
new java/util/Scanner
dup
getstatic java/lang/System/in Ljava/io/InputStream;
invokespecial java/util/Scanner/<init>(Ljava/io/InputStream;)V
invokevirtual java/util/Scanner/nextDouble()D
dstore 0
getstatic java/lang/System/out Ljava/io/PrintStream;
ldc "a = "
invokevirtual java/io/PrintStream/print(Ljava/lang/String;)V
getstatic java/lang/System/out Ljava/io/PrintStream;
dload 0
invokevirtual java/io/PrintStream/print(D)V
getstatic java/lang/System/out Ljava/io/PrintStream;
ldc ", b = "
invokevirtual java/io/PrintStream/print(Ljava/lang/String;)V
getstatic java/lang/System/out Ljava/io/PrintStream;
dload 2
invokevirtual java/io/PrintStream/print(D)V
getstatic java/lang/System/out Ljava/io/PrintStream;
ldc ", c = "
invokevirtual java/io/PrintStream/print(Ljava/lang/String;)V
getstatic java/lang/System/out Ljava/io/PrintStream;
dload 4
invokevirtual java/io/PrintStream/print(D)V
getstatic java/lang/System/out Ljava/io/PrintStream;
ldc "\n"
invokevirtual java/io/PrintStream/print(Ljava/lang/String;)V
getstatic java/lang/System/out Ljava/io/PrintStream;
ldc "d = "
invokevirtual java/io/PrintStream/print(Ljava/lang/String;)V
getstatic java/lang/System/out Ljava/io/PrintStream;
fload 6
invokevirtual java/io/PrintStream/print(F)V
getstatic java/lang/System/out Ljava/io/PrintStream;
ldc ", e = "
invokevirtual java/io/PrintStream/print(Ljava/lang/String;)V
getstatic java/lang/System/out Ljava/io/PrintStream;
fload 7
invokevirtual java/io/PrintStream/print(F)V
getstatic java/lang/System/out Ljava/io/PrintStream;
ldc ", f = "
invokevirtual java/io/PrintStream/print(Ljava/lang/String;)V
getstatic java/lang/System/out Ljava/io/PrintStream;
fload 10
invokevirtual java/io/PrintStream/print(F)V
getstatic java/lang/System/out Ljava/io/PrintStream;
ldc "\n"
invokevirtual java/io/PrintStream/print(Ljava/lang/String;)V
getstatic java/lang/System/out Ljava/io/PrintStream;
ldc "g = "
invokevirtual java/io/PrintStream/print(Ljava/lang/String;)V
getstatic java/lang/System/out Ljava/io/PrintStream;
iload 8
invokevirtual java/io/PrintStream/print(I)V
getstatic java/lang/System/out Ljava/io/PrintStream;
ldc ", h = "
invokevirtual java/io/PrintStream/print(Ljava/lang/String;)V
getstatic java/lang/System/out Ljava/io/PrintStream;
iload 9
invokevirtual java/io/PrintStream/print(I)V
getstatic java/lang/System/out Ljava/io/PrintStream;
ldc ", i = "
invokevirtual java/io/PrintStream/print(Ljava/lang/String;)V
getstatic java/lang/System/out Ljava/io/PrintStream;
iload 11
invokevirtual java/io/PrintStream/print(I)V
getstatic java/lang/System/out Ljava/io/PrintStream;
ldc "\n"
invokevirtual java/io/PrintStream/print(Ljava/lang/String;)V
return
.end method
